piptools/__init__.py
piptools/__main__.py
piptools/build.py
piptools/cache.py
piptools/exceptions.py
piptools/locations.py
piptools/logging.py
piptools/py.typed
piptools/resolver.py
piptools/subprocess_utils.py
piptools/sync.py
piptools/utils.py
piptools/writer.py
piptools/_compat/__init__.py
piptools/_compat/pip_compat.py
piptools/repositories/__init__.py
piptools/repositories/base.py
piptools/repositories/local.py
piptools/repositories/pypi.py
piptools/scripts/__init__.py
piptools/scripts/compile.py
piptools/scripts/options.py
piptools/scripts/sync.py
pip_tools-7.4.0.dist-info/LICENSE
pip_tools-7.4.0.dist-info/METADATA
pip_tools-7.4.0.dist-info/WHEEL
pip_tools-7.4.0.dist-info/entry_points.txt
pip_tools-7.4.0.dist-info/top_level.txt
pip_tools-7.4.0.dist-info/RECORD
