Metadata-Version: 2.1
Name: pip-tools
Version: 7.4.0
Summary: pip-tools keeps your pinned dependencies fresh.
Author-email: Vincent Driessen <me@nvie.com>
License: BSD
Project-URL: homepage, https://github.com/jazzband/pip-tools/
Project-URL: documentation, https://pip-tools.readthedocs.io/en/latest/
Project-URL: repository, https://github.com/jazzband/pip-tools
Project-URL: changelog, https://github.com/jazzband/pip-tools/releases
Keywords: pip,requirements,packaging
Classifier: Development Status :: 5 - Production/Stable
Classifier: Environment :: Console
Classifier: Intended Audience :: Developers
Classifier: Intended Audience :: System Administrators
Classifier: License :: OSI Approved :: BSD License
Classifier: Operating System :: OS Independent
Classifier: Programming Language :: Python :: 3 :: Only
Classifier: Programming Language :: Python :: 3
Classifier: Programming Language :: Python :: 3.10
Classifier: Programming Language :: Python :: 3.11
Classifier: Programming Language :: Python :: 3.8
Classifier: Programming Language :: Python :: 3.9
Classifier: Programming Language :: Python :: Implementation :: CPython
Classifier: Programming Language :: Python :: Implementation :: PyPy
Classifier: Programming Language :: Python
Classifier: Topic :: Software Development :: Quality Assurance
Classifier: Topic :: Software Development :: Testing
Classifier: Topic :: System :: Systems Administration
Classifier: Topic :: Utilities
Classifier: Typing :: Typed
Requires-Python: >=3.8
License-File: LICENSE
Requires-Dist: build>=1.0.0
Requires-Dist: click>=8
Requires-Dist: pip>=22.2
Requires-Dist: pyproject_hooks
Requires-Dist: tomli; python_version < "3.11"
Requires-Dist: setuptools
Requires-Dist: wheel
Provides-Extra: testing
Requires-Dist: pytest>=7.2.0; extra == "testing"
Requires-Dist: pytest-rerunfailures; extra == "testing"
Requires-Dist: pytest-xdist; extra == "testing"
Requires-Dist: tomli-w; extra == "testing"
Requires-Dist: flit_core<4,>=2; extra == "testing"
Requires-Dist: poetry_core>=1.0.0; extra == "testing"
Provides-Extra: coverage
Requires-Dist: covdefaults; extra == "coverage"
Requires-Dist: pytest-cov; extra == "coverage"
